corstream/__init__.py
corstream/core.py
corstream/ops/__init__.py
corstream/ops/asyncflow/__init__.py
corstream/ops/asyncflow/map_async.py
corstream/ops/control/__init__.py
corstream/ops/control/catch.py
corstream/ops/control/retry.py
corstream/ops/control/throttle.py
corstream/ops/diagnostic/__init__.py
corstream/ops/diagnostic/log.py
corstream/ops/transform/__init__.py
corstream/ops/transform/batch.py
corstream/ops/transform/filter.py
corstream/ops/transform/map.py
corstream/sinks/__init__.py
corstream/sinks/terminal/__init__.py
corstream/sinks/terminal/for_each.py
corstream/sinks/terminal/reduce.py
corstream/sinks/terminal/to_list.py
corstream-0.1.0a1.dist-info/LICENSE
corstream-0.1.0a1.dist-info/METADATA
corstream-0.1.0a1.dist-info/WHEEL
corstream-0.1.0a1.dist-info/RECORD
