Metadata-Version: 2.3
Name: corstream
Version: 0.1.0a1
Summary: A coroutine composition framework for declarative async pipelines in Python
License: MIT
Keywords: asyncio,streams,pipelines,functional,coroutines,declarative
Author: Shiv
Author-email: shiv@zerobytes.fr
Requires-Python: >=3.9,<4.0
Classifier: Development Status :: 3 - Alpha
Classifier: Intended Audience :: Developers
Classifier: License :: OSI Approved :: MIT License
Classifier: Programming Language :: Python :: 3
Classifier: Programming Language :: Python :: 3.9
Classifier: Programming Language :: Python :: 3.10
Classifier: Programming Language :: Python :: 3.11
Classifier: Programming Language :: Python :: 3.12
Classifier: Programming Language :: Python :: 3.13
Classifier: Topic :: Software Development :: Libraries
Classifier: Typing :: Typed
Project-URL: Documentation, https://github.com/shivkun/corstream#readme
Project-URL: Homepage, https://github.com/shivkun/corstream
Project-URL: Repository, https://github.com/shivkun/corstream
